cgse_core/__init__.py
cgse_core/settings.yaml
egse/confman/__init__.py
egse/confman/__main__.py
egse/confman/confman.yaml
egse/confman/confman_cs.py
egse/logger/__init__.py
egse/logger/__main__.py
egse/logger/log_cs.py
egse/procman/__init__.py
egse/procman/procman.yaml
egse/procman/procman_cs.py
egse/storage/__init__.py
egse/storage/__main__.py
egse/storage/persistence.py
egse/storage/storage.yaml
egse/storage/storage_cs.py
scripts/_start.py
scripts/_status.py
scripts/_stop.py
scripts/cgse.py
scripts/services.py
cgse_core-2025.0.9.dist-info/METADATA
cgse_core-2025.0.9.dist-info/WHEEL
cgse_core-2025.0.9.dist-info/entry_points.txt
cgse_core-2025.0.9.dist-info/RECORD
